<?xml version="1.0" encoding="UTF-8" ?>
<exportFile>
    <fileName>exportConfig</fileName>
    <!--exportType 0:EXCEL_2007,1:CSV-->
    <exportType>0</exportType>
    <!--title导出展示的列title名,alias对应别名，映射的字段名,width对应列的宽度,export表示是否导出0不导出、1导出、默认为导出-->
    <cell>
        <title>API_ID</title>
        <alias>id</alias>
        <width>8500</width>
        <export>1</export>
    </cell>
    <cell>
        <title>BACKEND_SYSTEM_ID</title>
        <alias>backendSystemId</alias>
        <width>8500</width>
        <export>1</export>
    </cell>
    <cell>
        <title>名称</title>
        <alias>name</alias>
        <width>4500</width>
        <export>1</export>
    </cell>
    <cell>
        <title>描述</title>
        <alias>description</alias>
        <width>6500</width>
        <export>1</export>
    </cell>
    <cell>
        <title>请求方式</title>
        <alias>method</alias>
        <width>2500</width>
        <export>1</export>
    </cell>
    <cell>
        <title>路径</title>
        <alias>path</alias>
        <width>6000</width>
        <export>1</export>
    </cell>
    <cell>
        <title>模式</title>
        <alias>scheme</alias>
        <width>3000</width>
        <export>1</export>
    </cell>
    <cell>
        <title>安全模式</title>
        <alias>securityScheme</alias>
        <width>3000</width>
        <export>1</export>
    </cell>
    <cell>
        <title>是否生效</title>
        <alias>state</alias>
        <width>3000</width>
        <export>1</export>
    </cell>
    <cell>
        <title>限流次数</title>
        <alias>limitCount</alias>
        <width>3000</width>
        <export>1</export>
    </cell>
    <cell>
        <title>限流时间</title>
        <alias>limitTime</alias>
        <width>3000</width>
        <export>1</export>
    </cell>
    <cell>
        <title>限流单位</title>
        <alias>limitUnit</alias>
        <width>3000</width>
        <export>1</export>
    </cell>
    <cell>
        <title>是否删除</title>
        <alias>isDelete</alias>
        <width>3000</width>
        <export>1</export>
    </cell>
</exportFile>